flight_ticket_mcp_server/__init__.py
flight_ticket_mcp_server/__main__.py
flight_ticket_mcp_server/main.py
flight_ticket_mcp_server/core/__init__.py
flight_ticket_mcp_server/core/flights.py
flight_ticket_mcp_server/tools/__init__.py
flight_ticket_mcp_server/tools/date_tools.py
flight_ticket_mcp_server/tools/flight_info_tools.py
flight_ticket_mcp_server/tools/flight_search_tools.py
flight_ticket_mcp_server/tools/flight_transfer_tools.py
flight_ticket_mcp_server/tools/simple_opensky_tools.py
flight_ticket_mcp_server/tools/weather_tools.py
flight_ticket_mcp_server/utils/__init__.py
flight_ticket_mcp_server/utils/api_client.py
flight_ticket_mcp_server/utils/cities_dict.py
flight_ticket_mcp_server/utils/date_utils.py
flight_ticket_mcp_server/utils/validators.py
flight_ticket_mcp_server-1.0.1.dist-info/licenses/LICENSE
flight_ticket_mcp_server-1.0.1.dist-info/METADATA
flight_ticket_mcp_server-1.0.1.dist-info/WHEEL
flight_ticket_mcp_server-1.0.1.dist-info/entry_points.txt
flight_ticket_mcp_server-1.0.1.dist-info/top_level.txt
flight_ticket_mcp_server-1.0.1.dist-info/RECORD
