Metadata-Version: 2.4
Name: flight-ticket-mcp-server
Version: 1.0.1
Summary: 一个基于模型上下文协议(MCP)的航空机票查询和管理服务器
Home-page: https://github.com/yourusername/flight-ticket-mcp-server
Author: Your Name
Author-email: Your Name <your.email@example.com>
License: MIT
Project-URL: Homepage, https://github.com/yourusername/flight-ticket-mcp-server
Project-URL: Repository, https://github.com/yourusername/flight-ticket-mcp-server
Project-URL: Documentation, https://github.com/yourusername/flight-ticket-mcp-server#readme
Project-URL: Issues, https://github.com/yourusername/flight-ticket-mcp-server/issues
Keywords: mcp,flight,ticket,search,ai,fastmcp
Classifier: Development Status :: 4 - Beta
Classifier: Intended Audience :: Developers
Classifier: License :: OSI Approved :: MIT License
Classifier: Programming Language :: Python :: 3
Classifier: Programming Language :: Python :: 3.11
Classifier: Programming Language :: Python :: 3.12
Classifier: Topic :: Software Development :: Libraries :: Python Modules
Classifier: Topic :: Internet :: WWW/HTTP :: Dynamic Content
Classifier: Topic :: Software Development :: Libraries :: Application Frameworks
Requires-Python: >=3.11
License-File: LICENSE
Requires-Dist: fastmcp>=2.8.0
Requires-Dist: pydantic>=2.0.0
Requires-Dist: requests>=2.31.0
Requires-Dist: python-dateutil>=2.8.0
Requires-Dist: pytz>=2023.3
Requires-Dist: uvicorn>=0.23.0
Requires-Dist: fastapi>=0.100.0
Requires-Dist: selenium>=4.0.0
Requires-Dist: geopy>=2.3.0
Provides-Extra: dev
Requires-Dist: pytest>=7.0.0; extra == "dev"
Requires-Dist: pytest-asyncio>=0.21.0; extra == "dev"
Requires-Dist: black>=23.0.0; extra == "dev"
Requires-Dist: isort>=5.12.0; extra == "dev"
Requires-Dist: flake8>=6.0.0; extra == "dev"
Requires-Dist: mypy>=1.0.0; extra == "dev"
Requires-Dist: build>=0.10.0; extra == "dev"
Requires-Dist: twine>=4.0.0; extra == "dev"
Dynamic: author
Dynamic: home-page
Dynamic: license-file
Dynamic: requires-python
